DOCUMENTATION.md
MANIFEST.in
README.md
setup.py
orqal/__init__.py
orqal/__init__.pyc
orqal/abstract.py
orqal/conf.py
orqal/example.json
orqal/web.py
orqal/worker.py
orqal/wrapper.py
orqal.egg-info/PKG-INFO
orqal.egg-info/SOURCES.txt
orqal.egg-info/dependency_links.txt
orqal.egg-info/entry_points.txt
orqal.egg-info/requires.txt
orqal.egg-info/top_level.txt
orqal.egg-info/zip-safe
orqal/__pycache__/__init__.cpython-36.pyc
orqal/__pycache__/__init__.cpython-37.pyc
orqal/__pycache__/abstract.cpython-36.pyc
orqal/__pycache__/abstract.cpython-37.pyc
orqal/__pycache__/conf.cpython-36.pyc
orqal/__pycache__/conf.cpython-37.pyc
orqal/__pycache__/web.cpython-36.pyc
orqal/__pycache__/worker.cpython-36.pyc
orqal/__pycache__/worker.cpython-37.pyc
orqal/__pycache__/wrapper.cpython-36.pyc
orqal/__pycache__/wrapper.cpython-37.pyc
orqal/static/.DS_Store
orqal/static/assets/.DS_Store
orqal/static/assets/css/orqual.css
orqal/static/assets/css/style.css
orqal/static/assets/css/style.css.map
orqal/static/assets/js/.DS_Store
orqal/static/assets/js/dashboard.js
orqal/static/assets/js/index.html
orqal/static/assets/js/main.js
orqal/static/assets/js/widgets.js
orqal/static/assets/js/init-scripts/.DS_Store
orqal/static/assets/js/init-scripts/chart-js/chartjs-init.js
orqal/static/assets/js/init-scripts/data-table/datatables-init.js
orqal/static/assets/js/init-scripts/flot-chart/.DS_Store
orqal/static/assets/js/init-scripts/flot-chart/curvedLines.js
orqal/static/assets/js/init-scripts/flot-chart/flot-chart-init.js
orqal/static/assets/js/init-scripts/flot-chart/flot-tooltip/jquery.flot.tooltip.min.js
orqal/static/assets/js/init-scripts/gmap/gmap.init.js
orqal/static/assets/js/init-scripts/peitychart/peitychart.init.js
orqal/static/assets/js/init-scripts/vector-map/vector.init.js
orqal/static/assets/scss/_gauge.scss
orqal/static/assets/scss/_socials.scss
orqal/static/assets/scss/_switches.scss
orqal/static/assets/scss/_variables.scss
orqal/static/assets/scss/_widgets.scss
orqal/static/assets/scss/style.scss
orqal/static/images/.gitignore
orqal/static/images/admin.jpg
orqal/static/images/dashboard.png
orqal/static/images/orqal.svg
orqal/static/images/orqal_logo.svg
